{"playlist": [
{"checked":true,"id":"437","title":"Я наткнулся на некоторый код который выглядел примерно так на днях","date":"Sep 12 2013 10:23","time":1378995836000},
{"checked":true,"id":"436","title":"I came across some code that looked something like this the other day","date":"Sep 12 2013 10:24","time":1378995862000},
{"checked":true,"id":"435","title":"Я думал мы узнавали друг друга","date":"Sep 12 2013 10:22","time":1378995764000},
{"checked":true,"id":"434","title":"I thought we were getting to know one another","date":"Sep 12 2013 10:23","time":1378995796000},
{"checked":true,"id":"433","title":"Я посылаю им гораздо менее загроможденную версию их объявления","date":"Sep 12 2013 10:21","time":1378995700000},
{"checked":true,"id":"432","title":"I send them a much less cluttered version of their ad","date":"Sep 12 2013 10:22","time":1378995723000},
{"checked":true,"id":"431","title":"Работа с этими людьми высасывает соки мою энергию","date":"Sep 12 2013 10:20","time":1378995611000},
{"checked":true,"id":"430","title":"Working with these people saps my energy","date":"Sep 12 2013 10:20","time":1378995639000},
{"checked":true,"id":"429","title":"Они обращаются со мной как будто я идиот","date":"Sep 12 2013 10:18","time":1378995501000},
{"checked":true,"id":"428","title":"They treat me like I am an idiot","date":"Sep 12 2013 10:18","time":1378995527000},
{"checked":true,"id":"427","title":"Мой клиент любит хвастаться","date":"Sep 12 2013 10:15","time":1378995354000},
{"checked":true,"id":"426","title":"My client loves to brag","date":"Sep 12 2013 10:16","time":1378995377000},
{"checked":true,"id":"425","title":"чтобы избежать двусмысленности","date":"Sep 12 2013 10:14","time":1378995274000},
{"checked":true,"id":"424","title":"to avoid ambiguity","date":"Sep 12 2013 10:15","time":1378995309000},
{"checked":true,"id":"422","title":"Positive It isnt here","date":"Sep 10 2013 11:38","time":1378827511000},
{"checked":true,"id":"421","title":"эта компания обречена","date":"Sep 10 2013 11:31","time":1378827092000},
{"checked":true,"id":"420","title":"this company is doomed","date":"Sep 10 2013 11:31","time":1378827110000},
{"checked":true,"id":"419","title":"своего рода афера","date":"Sep 10 2013 11:26","time":1378826815000},
{"checked":true,"id":"418","title":"some sort of scam","date":"Sep 10 2013 11:27","time":1378826836000},
{"checked":true,"id":"417","title":"они напоминают","date":"Sep 10 2013 11:24","time":1378826697000},
{"checked":true,"id":"416","title":"theyre reminiscent of","date":"Sep 10 2013 11:25","time":1378826723000},
{"checked":true,"id":"415","title":"Я не должен ничего обосновывать оправдывать подтверждать","date":"Sep 10 2013 10:51","time":1378824663000},
{"checked":true,"id":"414","title":"I dont have to justify anything","date":"Sep 10 2013 10:51","time":1378824686000},
{"checked":true,"id":"413","title":"Этот действительно загроможден захламлен","date":"Sep 10 2013 10:44","time":1378824255000},
{"checked":true,"id":"412","title":"this one is really cluttered","date":"Sep 10 2013 10:44","time":1378824274000},
{"checked":true,"id":"423","title":"несомненно это не здесь","date":"Sep 10 2013 11:38","time":1378827488000},
{"checked":true,"id":"411","title":"вы поможете минимизировать любые беспокойства которые клиент может иметь","date":"Sep 10 2013 10:00","time":1378821655000},
{"checked":true,"id":"410","title":"you help to minimize any anxiety the client may have","date":"Sep 10 2013 10:01","time":1378821688000},
{"checked":true,"id":"409","title":"слишком часто общение напряженно с самого начала","date":"Sep 10 2013 09:56","time":1378821375000},
{"checked":true,"id":"408","title":"too often communication is strained from the start","date":"Sep 10 2013 09:56","time":1378821405000},
{"checked":true,"id":"407","title":"преимущества наличия случайных небрежных повседневных нерабочих разговоров","date":"Sep 10 2013 09:49","time":1378820976000},
{"checked":true,"id":"406","title":"the benefits of having casual non-business conversations","date":"Sep 10 2013 09:50","time":1378821042000},
{"checked":true,"id":"405","title":"обмен знаниями с нашими коллегами сверстниками","date":"Sep 10 2013 09:42","time":1378820532000},
{"checked":true,"id":"404","title":"exchange knowledge with our peers","date":"Sep 10 2013 09:44","time":1378820655000},
{"checked":true,"id":"403","title":"плохая коммуникация это верный способ повредить любой проект","date":"Sep 10 2013 09:37","time":1378820255000},
{"checked":true,"id":"402","title":"poor communication is a surefire way to damage any project","date":"Sep 10 2013 09:38","time":1378820324000},
{"checked":true,"id":"401","title":"это должно быть особенно удобно для","date":"Sep 09 2013 09:59","time":1378735162000},
{"checked":true,"id":"400","title":"this should come especially handy for","date":"Sep 09 2013 09:59","time":1378735189000},
{"checked":true,"id":"399","title":"тонкие различия дизайна для предстоящего iphone 5S","date":"Sep 09 2013 09:58","time":1378735092000},
{"checked":true,"id":"398","title":"subtle design distinctions for the forth coming iphone 5s","date":"Sep 09 2013 09:58","time":1378735117000},
{"checked":true,"id":"397","title":"дoобавить запись с ключом имя и значением Джон","date":"Sep 09 2013 09:56","time":1378735009000},
{"checked":true,"id":"396","title":"add entry with key name and value John","date":"Sep 09 2013 09:57","time":1378735048000},
{"checked":true,"id":"395","title":"особенный своеобразный кодер уверен что это вы может иметь вопрос","date":"Sep 09 2013 09:54","time":1378734843000},
{"checked":true,"id":"394","title":"A peculiar coder I bet you are might have a question","date":"Sep 09 2013 09:54","time":1378734890000},
{"checked":true,"id":"393","title":"Написание серверных кусков выходит за рамки этой книги","date":"Sep 06 2013 16:19","time":1378498768000},
{"checked":true,"id":"392","title":"writing the server bits is beyond the scope of this book","date":"Sep 06 2013 16:20","time":1378498824000},
{"checked":true,"id":"391","title":"мы упомянули это раньше но стоит повторить","date":"Sep 06 2013 16:13","time":1378498409000},
{"checked":true,"id":"390","title":"We mentioned it before but it bears repeating","date":"Sep 06 2013 16:13","time":1378498438000},
{"checked":true,"id":"389","title":"мы утверждаем что он обеспечивает большие преимущества делая ваше приложение более легким в расширении","date":"Sep 06 2013 16:04","time":1378497888000},
{"checked":true,"id":"388","title":"we ll claim that it delivers great benefits in making your app easier to extend maintain and test","date":"Sep 06 2013 16:05","time":1378497925000},
{"checked":true,"id":"387","title":"Другие люди сотрудничающие на вашем проекте будут иметь мгновенную помощь в понимании того что вы написали","date":"Sep 06 2013 15:58","time":1378497487000},
{"checked":true,"id":"386","title":"Other folks collaborating on your project will have an instant leg up on understanding what you ve written","date":"Sep 06 2013 15:58","time":1378497520000},
{"checked":true,"id":"385","title":"наконец модель уведомляет представление о том что произошло изменение так что он может обновлять то что он отображает","date":"Sep 06 2013 15:49","time":1378496984000},
{"checked":true,"id":"384","title":"finally the model notifies the view that a change has occurred so that it can update what it displays","date":"Sep 06 2013 15:50","time":1378497050000},
{"checked":true,"id":"383","title":"взгляните на обоих и решите, какой подход является правильным для Вас","date":"Sep 06 2013 15:28","time":1378495720000},
{"checked":true,"id":"382","title":"take a look at both and decide which approach is right for you","date":"Sep 06 2013 15:29","time":1378495743000},
{"checked":true,"id":"381","title":"эта функция будет служить вам хорошо","date":"Sep 06 2013 15:26","time":1378495572000},
{"checked":true,"id":"380","title":"this function will serve you well","date":"Sep 06 2013 15:26","time":1378495599000},
{"checked":true,"id":"379","title":"это позволяет вам много удобных методов для Bootstrap функциональности","date":"Sep 06 2013 15:23","time":1378495421000},
{"checked":true,"id":"378","title":"that allows you many convenience methods for Bootstrap functionality","date":"Sep 06 2013 15:24","time":1378495442000},
{"checked":true,"id":"377","title":"инициализатор переменной является избыточным излишним","date":"Sep 06 2013 15:06","time":1378494417000},
{"checked":true,"id":"376","title":"variable initializer is redundant","date":"Sep 06 2013 15:07","time":1378494457000},
{"checked":true,"id":"375","title":"смотрите если каждый элемент массива соответствует логическому утверждению","date":"Sep 06 2013 09:12","time":1378473147000},
{"checked":true,"id":"374","title":"see if every element in the array satisfies a predicate","date":"Sep 06 2013 09:13","time":1378473188000},
{"checked":true,"id":"373","title":"повысьте ваши навыки программирования","date":"Sep 06 2013 09:11","time":1378473065000},
{"checked":true,"id":"372","title":"level up your programming skills","date":"Sep 06 2013 09:11","time":1378473095000},
{"checked":true,"id":"371","title":"повторение всех необходимых утверждений каждый раз является утомительным и подверженным ошибкам","date":"Sep 06 2013 09:04","time":1378472653000},
{"checked":true,"id":"370","title":"repeating all the necessary statements every time is tedious and error-prone","date":"Sep 06 2013 09:04","time":1378472686000},
{"checked":true,"id":"369","title":"Красноречивый JavaScript","date":"Sep 06 2013 09:02","time":1378472569000},
{"checked":true,"id":"368","title":"Eloquent JavaScript","date":"Sep 06 2013 09:03","time":1378472593000},
{"checked":true,"id":"367","title":"пороховая бочка","date":"Sep 06 2013 09:01","time":1378472510000},
{"checked":true,"id":"366","title":"powder keg","date":"Sep 06 2013 09:02","time":1378472530000},
{"checked":true,"id":"365","title":"выполнять обязательства","date":"Sep 06 2013 09:00","time":1378472426000},
{"checked":true,"id":"364","title":"keep commitments","date":"Sep 06 2013 09:01","time":1378472481000},
{"checked":true,"id":"363","title":"Старшина используется для создания каркаса лесов вашего приложение для вас","date":"Aug 30 2013 17:35","time":1377898521000},
{"checked":true,"id":"362","title":"Yeoman is used to generate the scaffolding of your app for you","date":"Aug 30 2013 17:35","time":1377898546000},
{"checked":true,"id":"361","title":"AngularJS имеет изворотливый эффективный и мощный набор функций","date":"Aug 30 2013 17:34","time":1377898454000},
{"checked":true,"id":"360","title":"AngularJS has a quirky efficient and powerful feature set","date":"Aug 30 2013 17:34","time":1377898485000},
{"checked":true,"id":"359","title":"Контроллер имеет метод который подключен к ngclick на некотором элементе","date":"Aug 29 2013 10:15","time":1377785736000},
{"checked":true,"id":"358","title":"controller has a method thats hooked up to ng-click on some element","date":"Aug 29 2013 10:15","time":1377785758000},
{"checked":true,"id":"357","title":"Вы используете простой последовательный интерфейс JavaScript для взаимодействия с основными LinkedIn типами данных","date":"Aug 29 2013 10:14","time":1377785644000},
{"checked":true,"id":"355","title":"Существует предостережение сравнения должны быть простыми чтобы вписаться в 25 мкс","date":"Aug 29 2013 10:12","time":1377785556000},
{"checked":true,"id":"356","title":"you use a simple consistent JavaScript interface to interact with the fundamental LinkedIn data types","date":"Aug 29 2013 10:14","time":1377785678000},
{"checked":true,"id":"354","title":"There is a caveat the comparisons need to be simple to fit into 25µs","date":"Aug 29 2013 10:13","time":1377785585000},
{"checked":true,"id":"353","title":"незаметный для человека и таким образом можно рассматривать как мгновенный","date":"Aug 29 2013 10:11","time":1377785471000},
{"checked":true,"id":"352","title":"is imperceptible to humans and thus can be considered as instant","date":"Aug 29 2013 10:11","time":1377785503000},
{"checked":true,"id":"350","title":"I dont suggest you shun JavaScript","date":"Aug 29 2013 10:10","time":1377785428000},
{"checked":true,"id":"349","title":"Но я помню проклятия JavaScript 15 лет назад","date":"Aug 29 2013 10:09","time":1377785355000},
{"checked":true,"id":"351","title":"Я не предлагаю вам избегать JavaScript","date":"Aug 29 2013 10:10","time":1377785405000},
{"checked":true,"id":"348","title":"But I remember cursing JavaScript 15 years ago","date":"Aug 29 2013 10:09","time":1377785376000},
{"checked":true,"id":"347","title":"Полезные запасные методы для CSS","date":"Aug 29 2013 10:07","time":1377785267000},
{"checked":true,"id":"346","title":"Useful Fallback Methods For CSS","date":"Aug 29 2013 10:08","time":1377785324000},
{"checked":true,"id":"345","title":"Наслаждайтесь функций которые оказываются полезны","date":"Aug 29 2013 10:06","time":1377785217000},
{"checked":true,"id":"344","title":"Enjoy functions that turn out to be useful","date":"Aug 29 2013 10:07","time":1377785241000},
{"checked":true,"id":"343","title":"Остерегайтесь всех случаев ниже","date":"Aug 29 2013 10:05","time":1377785144000},
{"checked":true,"id":"342","title":"Beware of all the cases below","date":"Aug 29 2013 10:06","time":1377785165000},
{"checked":true,"id":"341","title":"краткий способ присвоения по умолчанию  альтернативные значения в JavaScript","date":"Aug 29 2013 10:04","time":1377785065000},
{"checked":true,"id":"340","title":"terse way of assigning default alternative values in JavaScript","date":"Aug 29 2013 10:04","time":1377785092000},
{"checked":true,"id":"339","title":"я полностью гадаю здесь но похоже","date":"Aug 29 2013 10:02","time":1377784978000},
{"checked":true,"id":"338","title":"I am totally guessing here but it looks like","date":"Aug 29 2013 10:03","time":1377785019000},
{"checked":true,"id":"337","title":"Если вы провалитесь делая это Угадайте кто получит вину","date":"Aug 26 2013 09:35","time":1377524107000},
{"checked":true,"id":"336","title":"If you fail to do so Guess who gets the blame","date":"Aug 26 2013 09:35","time":1377524144000},
{"checked":true,"id":"335","title":"Вам придется скрести рвать когтями царапать тащить скрежетать рвать и выводить распутывать каждое требование из их немного наивной души сущности","date":"Aug 26 2013 09:33","time":1377524017000},
{"checked":true,"id":"334","title":"You will have to claw scrape drag gnash rip and extricate every requirement from their naive little souls","date":"Aug 26 2013 09:34","time":1377524064000},
{"checked":true,"id":"333","title":"Вся разработка программного обеспечения являеeтся повторяющейся","date":"Aug 26 2013 09:31","time":1377523870000},
{"checked":true,"id":"332","title":"All software development is iterative","date":"Aug 26 2013 09:32","time":1377523948000},
{"checked":true,"id":"331","title":"Я предполагаю что с смыть, повторить заявлениями вы имеете в виду гибкие методологии","date":"Aug 26 2013 09:28","time":1377523728000},
{"checked":true,"id":"330","title":"I assume with the Rinse Repeat statement youre implying an agile methodology","date":"Aug 26 2013 09:30","time":1377523825000},
{"checked":true,"id":"329","title":"Попросите ваших программистов начать превращать ваши требования в программное обеспечение","date":"Aug 26 2013 09:27","time":1377523650000},
{"checked":true,"id":"328","title":"Have your programmers start turning your requirements into software","date":"Aug 26 2013 09:28","time":1377523689000},
{"checked":true,"id":"327","title":"Попросите вашего HTML CSS разработчика превратить его в разметку","date":"Aug 26 2013 09:25","time":1377523557000},
{"checked":true,"id":"326","title":"Have your HTML CSS developer turn it into markup","date":"Aug 26 2013 09:26","time":1377523592000},
{"checked":true,"id":"325","title":"Определение требований Варианты использования Визуальная проверка концепции Получить одобрение клиента Смыть повторить","date":"Aug 26 2013 09:23","time":1377523411000},
{"checked":true,"id":"324","title":"Define requirements Use cases Visual proof of concept Get client sign off  Rinse  Repeat","date":"Aug 26 2013 09:24","time":1377523491000},
{"checked":true,"id":"323","title":"Подготовочный сайт позволит будущим релизам быть тестированными до перемещения его в производство","date":"Aug 26 2013 09:19","time":1377523165000},
{"checked":true,"id":"322","title":"A staging site will allow for future releases to be tested prior to moving it to production","date":"Aug 26 2013 09:21","time":1377523297000},
{"checked":true,"id":"321","title":"Программисты, как известно, плохи в UI","date":"Aug 26 2013 09:17","time":1377523024000},
{"checked":true,"id":"320","title":"Programmers are notoriously bad at UI","date":"Aug 26 2013 09:17","time":1377523052000},
{"checked":true,"id":"319","title":"Я просто хочу знать, как профессионалы обычно управляются с этим","date":"Aug 26 2013 09:15","time":1377522956000},
{"checked":true,"id":"318","title":"I just want to know how a professional normally handles it","date":"Aug 26 2013 09:16","time":1377522987000},
{"checked":true,"id":"317","title":"таким образом я полагаю что было бы неплохо сдeлать быстрый пилотный проект","date":"Aug 26 2013 09:13","time":1377522793000},
{"checked":true,"id":"316","title":"so I figure it might be good to do a quick pilot project","date":"Aug 26 2013 09:14","time":1377522847000},
{"checked":true,"id":"315","title":"Вполне вероятно что любой framework вы выбираете не будет активно поддерживаться через год","date":"Aug 26 2013 09:09","time":1377522592000},
{"checked":true,"id":"314","title":"It's likely that any frameworkk you choose won't be actively maintained in a year","date":"Aug 26 2013 09:10","time":1377522622000},
{"checked":true,"id":"313","title":"Перестаньте ныть о новых JSFrameworks","date":"Aug 26 2013 09:06","time":1377522389000},
{"checked":true,"id":"312","title":"Stop Whining About New JSFrameworks","date":"Aug 26 2013 09:08","time":1377522489000},
{"checked":true,"id":"311","title":"Сущность XML это","date":"Aug 22 2013 17:35","time":1377207320000},
{"checked":true,"id":"310","title":"The essence of XML is this","date":"Aug 22 2013 17:35","time":1377207357000},
{"checked":true,"id":"309","title":"Затем это выходит из под контроля в полном хаосе","date":"Aug 22 2013 17:34","time":1377207269000},
{"checked":true,"id":"308","title":"Then it spirals out of control into utter chaos","date":"Aug 22 2013 17:34","time":1377207292000},
{"checked":true,"id":"307","title":"зависимая от платформы тропа страдания, отчаяние, ужаса и безумия","date":"Aug 22 2013 17:33","time":1377207204000},
{"checked":true,"id":"306","title":"platform dependant trail of misery despair horror and madness.","date":"Aug 22 2013 17:33","time":1377207236000},
{"checked":true,"id":"305","title":"Эффект как этот может быть достигнут только путем обмана Javascript","date":"Aug 22 2013 17:32","time":1377207132000},
{"checked":true,"id":"304","title":"An effect like this can be achieved only through Javascript trickery","date":"Aug 22 2013 17:32","time":1377207168000},
{"checked":true,"id":"303","title":"Один из способов чтобы сделать его настолько простым что там очевидно нет недостатков и наоборот чтобы сделать его настолько сложным что нет никаких очевидных недостатков","date":"Aug 21 2013 09:48","time":1377092922000},
{"checked":true,"id":"302","title":"One way is to make it so simple that there are obviously no deficiencies and the other way is to make it so complicated that there are no obvious deficiencies","date":"Aug 21 2013 09:49","time":1377092983000},
{"checked":true,"id":"301","title":"Одна из изящных отличных  особенностей AngularJS","date":"Aug 21 2013 09:40","time":1377092437000},
{"checked":true,"id":"300","title":"One of the nifty feature of AngularJS","date":"Aug 21 2013 09:41","time":1377092493000},
{"checked":true,"id":"299","title":"Один изящный отличный  трюк","date":"Aug 21 2013 09:37","time":1377092261000},
{"checked":true,"id":"298","title":"One nifty trick","date":"Aug 21 2013 09:38","time":1377092294000},
{"checked":true,"id":"297","title":"что означает до тех пор как класс CSS присутствует в вашем HTML коде то анимация может быть напрямую подключена в действующее приложение","date":"Aug 21 2013 09:33","time":1377091986000},
{"checked":true,"id":"296","title":"which means so long as a CSS class is present in your HTML code then animations can be directly hooked into a working application","date":"Aug 21 2013 09:33","time":1377092033000},
{"checked":true,"id":"295","title":"где вы можете иметь временное импровизированное  обсуждение","date":"Aug 21 2013 09:29","time":1377091757000},
{"checked":true,"id":"294","title":"where you can have makeshift discussions","date":"Aug 21 2013 09:29","time":1377091783000},
{"checked":true,"id":"293","title":"Вот краткое изложение того как мы собираемся структурировать директивы","date":"Aug 21 2013 09:27","time":1377091672000},
{"checked":true,"id":"292","title":"Here is a quick rundown of the way were going to structure the directive","date":"Aug 21 2013 09:28","time":1377091704000},
{"checked":true,"id":"291","title":"Директива это поведение которыо должно быть вызвано запущено когда определенные HTML конструкции встречаются в процессе компиляции","date":"Aug 21 2013 09:26","time":1377091571000},
{"checked":true,"id":"290","title":"A directive is a behavior which should be triggered when specific HTML constructs are encountered in the compilation process","date":"Aug 21 2013 09:26","time":1377091618000},
{"checked":true,"id":"289","title":"Директива может быть помещена в имена элементов атрибуты имена классов а также комментарии","date":"Aug 21 2013 09:23","time":1377091425000},
{"checked":true,"id":"288","title":"The directives can be placed in element names attributes class names as well as comments","date":"Aug 21 2013 09:24","time":1377091476000},
{"checked":true,"id":"287","title":"Некоторые из вопросов с этим подходом чтение пользовательского ввода и слияние eго с данными удаление пользовательского ввода путем eго перезаписи","date":"Aug 21 2013 09:21","time":1377091266000},
{"checked":true,"id":"286","title":"Some of the issues with this approach are reading user input and merging it with data clobbering user input by overwriting it","date":"Aug 21 2013 09:22","time":1377091358000},
{"checked":true,"id":"285","title":"Они деактивировали кнопку чтобы остановить людей от ее использования","date":"Aug 20 2013 09:44","time":1377006266000},
{"checked":true,"id":"284","title":"They GREYED OUT the print button to stop people using it","date":"Aug 20 2013 09:44","time":1377006291000},
{"checked":true,"id":"283","title":"Исследование дает представление о теории эволюции","date":"Aug 20 2013 09:42","time":1377006151000},
{"checked":true,"id":"282","title":"The research gives insight into the theory of evolution","date":"Aug 20 2013 09:42","time":1377006172000},
{"checked":true,"id":"281","title":"проницательные глубокие ценные комментарии","date":"Aug 20 2013 09:41","time":1377006102000},
{"checked":true,"id":"280","title":"insightful comments","date":"Aug 20 2013 09:41","time":1377006118000},
{"checked":true,"id":"279","title":"Да Это тот случай","date":"Aug 20 2013 09:40","time":1377006051000},
{"checked":true,"id":"278","title":"Yes This is the case","date":"Aug 20 2013 09:41","time":1377006073000},
{"checked":true,"id":"277","title":"Постарайтесь не зацикливаться останавливаться на терминологии","date":"Aug 20 2013 09:39","time":1377005998000},
{"checked":true,"id":"276","title":"Try not to dwell on the terminology","date":"Aug 20 2013 09:40","time":1377006018000},
{"checked":true,"id":"275","title":"Этот плагин является уязвимым","date":"Aug 20 2013 09:39","time":1377005955000},
{"checked":true,"id":"274","title":"this plugin is vulnerable","date":"Aug 20 2013 09:39","time":1377005975000},
{"checked":true,"id":"273","title":"устаревшая ОШИБКА","date":"Aug 20 2013 09:38","time":1377005900000},
{"checked":true,"id":"272","title":"DEPRECATED ERROR","date":"Aug 20 2013 09:38","time":1377005924000},
{"checked":true,"id":"271","title":"Я сделал кучу копания сегодня и  Это своего рода выше моего понимания но я думаю что проблема связана с тем что я использую ng-bootstrap","date":"Aug 20 2013 09:37","time":1377005830000},
{"checked":true,"id":"270","title":"I did a bunch of digging around today and its kind of over my head but I think the issue has to do with the fact that I am using the ng-bootstrap","date":"Aug 20 2013 09:37","time":1377005872000},
{"checked":true,"id":"269","title":"Я до сих пор в тупике пень к сожалению","date":"Aug 20 2013 09:35","time":1377005739000},
{"checked":true,"id":"268","title":"Im still stumped unfortunately","date":"Aug 20 2013 09:36","time":1377005766000},
{"checked":true,"id":"267","title":"офлайн веб-приложение вращается вокруг кэша файла манифеста","date":"Aug 20 2013 09:34","time":1377005648000},
{"checked":true,"id":"266","title":"An offline web application revolves around a cache manifest file","date":"Aug 20 2013 09:34","time":1377005669000},
{"checked":true,"id":"265","title":"В простейшем случае","date":"Aug 20 2013 09:32","time":1377005563000},
{"checked":true,"id":"264","title":"at its simplest","date":"Aug 20 2013 09:32","time":1377005579000},
{"checked":true,"id":"263","title":"На первый взгляд это звучит как противоречие","date":"Aug 20 2013 09:31","time":1377005518000},
{"checked":true,"id":"262","title":"At first glance it sounds like a contradiction","date":"Aug 20 2013 09:32","time":1377005540000},
{"checked":true,"id":"261","title":"борьба с нг-повтор","date":"Aug 20 2013 09:31","time":1377005461000},
{"checked":true,"id":"260","title":"wrestling with ng-repeat","date":"Aug 20 2013 09:31","time":1377005482000},
{"checked":true,"id":"259","title":"Документация AngularJS на самом деле не исчерпывающая то есть требует фоновые знания","date":"Aug 20 2013 09:29","time":1377005363000},
{"checked":true,"id":"258","title":"The AngularJS documentation is not really exhaustive ie demands background knowledge","date":"Aug 20 2013 09:30","time":1377005403000},
{"checked":true,"id":"257","title":"Но если вы поиграйте с ним вы увидите результаты могут быть неожиданными","date":"Aug 20 2013 09:27","time":1377005235000},
{"checked":true,"id":"256","title":"But if you play around with it you'll see results can be unexpected","date":"Aug 20 2013 09:28","time":1377005285000},
{"checked":true,"id":"255","title":"Есть слишком много предположений и это не полезно вообще","date":"Aug 16 2013 10:59","time":1376665159000},
{"checked":true,"id":"254","title":"there are too many assumptions and its not helpful at all","date":"Aug 16 2013 10:59","time":1376665191000},
{"checked":true,"id":"253","title":"Я склонен думать достойным вариантом является использование простой директивы для создания подключения jQueryUI ползунков","date":"Aug 16 2013 10:57","time":1376665069000},
{"checked":true,"id":"252","title":"Im inclined to think a decent option is to use a simple directive to create hook-up the jQueryUI sliders","date":"Aug 16 2013 10:58","time":1376665102000},
{"checked":true,"id":"251","title":"Но вернемся к точке","date":"Aug 16 2013 10:55","time":1376664931000},
{"checked":true,"id":"250","title":"But back to the point","date":"Aug 16 2013 10:55","time":1376664950000},
{"checked":true,"id":"249","title":"Документация на самом деле не исчерпывающая","date":"Aug 16 2013 10:54","time":1376664878000},
{"checked":true,"id":"248","title":"documentation is not really exhaustive","date":"Aug 16 2013 10:55","time":1376664900000},
{"checked":true,"id":"247","title":"Но мои сомнения, как внедрить зависимости","date":"Aug 16 2013 10:53","time":1376664817000},
{"checked":true,"id":"246","title":"But my doubt is how to inject the dependencies","date":"Aug 16 2013 10:54","time":1376664847000},
{"checked":true,"id":"245","title":"Здесь собрание общих предостережений вы можете столкнуться во время разработки","date":"Aug 16 2013 10:52","time":1376664728000},
{"checked":true,"id":"244","title":"Here is a collection of common caveats you may run into during your development","date":"Aug 16 2013 10:52","time":1376664759000},
{"checked":true,"id":"243","title":"сосредоточиться исключительно на их механике","date":"Aug 16 2013 10:50","time":1376664638000},
{"checked":true,"id":"242","title":"focus solely on their mechanics","date":"Aug 16 2013 10:51","time":1376664678000},
{"checked":true,"id":"241","title":"работа над MP3 и H264 поддежкой Firefox  в стадии реализации","date":"Aug 16 2013 10:48","time":1376664539000},
{"checked":true,"id":"240","title":"work for MP3 and H264 support in Firefox is underway","date":"Aug 16 2013 10:49","time":1376664564000},
{"checked":true,"id":"239","title":"Единственный недостаток в том что вы должны изменить все свои маршруты","date":"Aug 16 2013 10:47","time":1376664468000},
{"checked":true,"id":"238","title":"The only downfall is you have to change all your routes","date":"Aug 16 2013 10:48","time":1376664500000},
{"checked":true,"id":"237","title":"Сценарий работает безупречно в IE не делает ничего В Firefox я в тупике","date":"Aug 16 2013 10:46","time":1376664380000},
{"checked":true,"id":"236","title":"Script works Flawlessly in IE does NOTHING in firefox Im stumped","date":"Aug 16 2013 10:47","time":1376664420000},
{"checked":true,"id":"235","title":"вы найдете что-то подобное что по крайней мере частично напоминает вашу проблему","date":"Aug 16 2013 10:44","time":1376664283000},
{"checked":true,"id":"234","title":"you find something similar that at least partially resembles your  problem","date":"Aug 16 2013 10:45","time":1376664338000},
{"checked":true,"id":"233","title":"Документы говорят очень заметно чтобы не использовать ready больше но использовать pageInit  вместо этого","date":"Aug 16 2013 10:42","time":1376664127000},
{"checked":true,"id":"232","title":"The docs say very prominently not to use ready any more but to use pageInit instead","date":"Aug 16 2013 10:43","time":1376664190000},
{"checked":true,"id":"231","title":"Как я могу исправить мой код","date":"Aug 16 2013 10:39","time":1376663962000},
{"checked":true,"id":"230","title":"How can I remedy my code","date":"Aug 16 2013 10:39","time":1376663989000},
{"checked":true,"id":"229","title":"В последнее время было много разговоров о мобильных оптимизированных сайтов","date":"Aug 16 2013 10:38","time":1376663882000},
{"checked":true,"id":"228","title":"Lately there has been a lot of talk about mobile optimised websites","date":"Aug 16 2013 10:38","time":1376663910000},
{"checked":true,"id":"227","title":"выполнения путь который привел к точке где код был приостановлен  давая нам проникновениe в суть понимание кода недостатки","date":"Aug 16 2013 10:34","time":1376663692000},
{"checked":true,"id":"226","title":"execution path that led to the point where code was paused giving us insights into the code flaws that caused the error","date":"Aug 16 2013 10:36","time":1376663786000},
{"checked":true,"id":"225","title":"Доступно также через гаечный ключ меню","date":"Aug 16 2013 10:31","time":1376663495000},
{"checked":true,"id":"224","title":"Also available through the wrench menu","date":"Aug 16 2013 10:31","time":1376663517000},
{"checked":true,"id":"223","title":"Для IE безвредно для других браузеров","date":"Aug 16 2013 10:30","time":1376663436000},
{"checked":true,"id":"222","title":"For IE harmless to other browsers","date":"Aug 16 2013 10:31","time":1376663462000},
{"checked":true,"id":"221","title":"ограничен крутой ценой","date":"Aug 16 2013 10:29","time":1376663374000},
{"checked":true,"id":"220","title":"limited by the steep price","date":"Aug 16 2013 10:30","time":1376663403000},
{"checked":true,"id":"219","title":"написать код который придерживается тех же стандартов руководств по стилю","date":"Aug 16 2013 10:28","time":1376663312000},
{"checked":true,"id":"218","title":"write code that adheres to the same standards style guides","date":"Aug 16 2013 10:29","time":1376663345000},
{"checked":true,"id":"217","title":"Мое отсутствие навыков CSS дает мне головную боль","date":"Aug 16 2013 10:26","time":1376663189000},
{"checked":true,"id":"216","title":"My lacking skills of CSS is giving me a headache","date":"Aug 16 2013 10:27","time":1376663221000},
{"checked":true,"id":"215","title":"Детали такие как управление отступа кода теперь может быть требовательный процесс в целом сборка завершится ошибкой","date":"Aug 16 2013 10:25","time":1376663102000},
{"checked":true,"id":"214","title":"Details such as controlling the indentation of code can now be a strict process as a whole build will fail if any part throws an error","date":"Aug 16 2013 10:25","time":1376663157000},
{"checked":true,"id":"213","title":"зная как использовать его эффективно можно ускорить рабочий процесс сам по себе","date":"Aug 16 2013 10:23","time":1376662981000},
{"checked":true,"id":"212","title":"knowing how to use it effectively can speed up your workflow on its own","date":"Aug 16 2013 10:23","time":1376663025000},
{"checked":true,"id":"211","title":"Некоторые люди осуждают расширение прототипов встроенных типов хотя","date":"Aug 16 2013 10:20","time":1376662846000},
{"checked":true,"id":"210","title":"Some people frown upon extending the prototype of built-in types though","date":"Aug 16 2013 10:21","time":1376662875000},
{"checked":true,"id":"209","title":"вы должны явно скопировать свойства объекта","date":"Aug 16 2013 10:19","time":1376662754000},
{"checked":true,"id":"208","title":"you must explicitly copy the properties of the object","date":"Aug 16 2013 10:19","time":1376662785000},
{"checked":true,"id":"207","title":"о неизменных примитивных значенях","date":"Aug 15 2013 11:02","time":1376578944000},
{"checked":true,"id":"206","title":"about immutable primitive values","date":"Aug 15 2013 11:02","time":1376578963000},
{"checked":true,"id":"205","title":"Когда текстовое поле остается пустым и пользователь пытается продолжить с действием добавления","date":"Aug 15 2013 11:00","time":1376578823000},
{"checked":true,"id":"204","title":"When textbox is left empty and the user attempts to proceed with the adding action","date":"Aug 15 2013 11:01","time":1376578911000},
{"checked":true,"id":"203","title":"ненавязчивый Javascript пример демонстрирующий  как обращаться и использовать","date":"Aug 15 2013 10:58","time":1376578736000},
{"checked":true,"id":"202","title":"unobtrusive Javascript example demonstrating how to handle and use","date":"Aug 15 2013 10:59","time":1376578764000},
{"checked":true,"id":"201","title":"вместо желания создать соблазнительный потребительский продукт","date":"Aug 15 2013 10:56","time":1376578619000},
{"checked":true,"id":"200","title":"rather than the desire to create a seductive consumer product","date":"Aug 15 2013 10:57","time":1376578645000},
{"checked":true,"id":"199","title":"Чтобы обойти эту проблему мы должны проверить сколько фотоснимков есть на странице и вызывать функцию только один раз после","date":"Aug 15 2013 10:54","time":1376578493000},
{"checked":true,"id":"198","title":"To get around this we should check how many images there are on the page and only fire the function once after all those images have been loaded","date":"Aug 15 2013 10:55","time":1376578521000},
{"checked":true,"id":"197","title":"Мне интересно есть ли менее многословный способ проверки который имеет тот же эффект","date":"Aug 15 2013 10:48","time":1376578107000},
{"checked":true,"id":"196","title":"Im wondering whether there is a less verbose way of checking that has the same effect","date":"Aug 15 2013 10:53","time":1376578401000},
{"checked":true,"id":"195","title":"При  последовательном подключении моей декларации это легко обслуживать что фактически присоединены к основному модулю","date":"Aug 15 2013 10:46","time":1376578007000},
{"checked":true,"id":"194","title":"By daisy chaining my declarations it is easy to maintain what actually is attached to the underlying module","date":"Aug 15 2013 10:47","time":1376578044000},
{"checked":true,"id":"193","title":"Предположительно подобно тому, что бэкенд отрендрит","date":"Aug 15 2013 10:45","time":1376577908000},
{"checked":true,"id":"192","title":"Presumably similar to what the backend would render","date":"Aug 15 2013 10:45","time":1376577947000},
{"checked":true,"id":"191","title":"но хорошо, я споткнулся на этом","date":"Aug 15 2013 10:43","time":1376577825000},
{"checked":true,"id":"190","title":"but well I stumbled on this","date":"Aug 15 2013 10:44","time":1376577856000},
{"checked":true,"id":"189","title":"Apple удалось передать глубину текстуры кнопки и иконки которые имитировали реальные объекты","date":"Aug 15 2013 10:31","time":1376577079000},
{"checked":true,"id":"188","title":"Apple managed to convey depth textures buttons and icons that mimicked real-life objects","date":"Aug 15 2013 10:32","time":1376577138000},
{"checked":true,"id":"187","title":"я печально наткнулся на этот пост который был сфабрикован с помощью наших конкурентов поэтому я хотел ответить сразу же","date":"Aug 14 2013 15:22","time":1376508124000},
{"checked":true,"id":"186","title":"i sadly came across this post that has been fabricated by our competitor so i wanted to reply immediately","date":"Aug 14 2013 15:24","time":1376508256000},
{"checked":true,"id":"185","title":"Я знаю это так как они посылают такою же тарабарщину для наших клиентов и перспективы время от времени и они пересылают их","date":"Aug 14 2013 15:19","time":1376507973000},
{"checked":true,"id":"184","title":"I know it as they send the same gibberish to our clients and prospects from time to time and they forward it to us laughing at their pathetic attempts to bad mouth us","date":"Aug 14 2013 15:20","time":1376508009000},
{"checked":true,"id":"183","title":"b тег должен быть использован в качестве последнего средства прибежища когда никакой другой тег не является более уместным","date":"Aug 14 2013 15:17","time":1376507840000},
{"checked":true,"id":"182","title":"b tag should be used as a LAST resort when no other tag is more appropriate","date":"Aug 14 2013 15:17","time":1376507879000},
{"checked":true,"id":"181","title":"В случае если он нуждается в разъяснении я наличии утра EST","date":"Aug 14 2013 15:15","time":1376507719000},
{"checked":true,"id":"180","title":"In case he needs any clarification Im avail mornings EST","date":"Aug 14 2013 15:15","time":1376507751000},
{"checked":true,"id":"179","title":"выделенный текст должен быть обозначен  em тегom","date":"Aug 14 2013 15:12","time":1376507554000},
{"checked":true,"id":"178","title":"emphasized text should be denoted with the em tag","date":"Aug 14 2013 15:13","time":1376507608000},
{"checked":true,"id":"177","title":"Автор не собирается шагать в это обсуждение","date":"Aug 14 2013 15:11","time":1376507463000},
{"checked":true,"id":"176","title":"author is not going to tread into that discussion","date":"Aug 14 2013 15:11","time":1376507494000},
{"checked":true,"id":"175","title":"Я не могу видеть нас отказавшихся от этой пользовательской базы в ближайшее время и мы должны действительно позволить себе","date":"Aug 14 2013 15:09","time":1376507393000},
{"checked":true,"id":"174","title":"I cant see us abandoning that user base any time soon and we should really allow ourselves to be experience what the average IE user come across with our platform","date":"Aug 14 2013 15:10","time":1376507430000},
{"checked":true,"id":"173","title":"На самом деле я бы боролся против обоих не использования IE и заставлять определенные рендеринги в IE для QA тестирования","date":"Aug 14 2013 15:06","time":1376507206000},
{"checked":true,"id":"172","title":"Actually I would contest against both not using IE and to force a certain rendering in IE for QA testing","date":"Aug 14 2013 15:07","time":1376507263000},
{"checked":true,"id":"171","title":"Это в значительной степени все что нам нужно сделать","date":"Aug 14 2013 15:02","time":1376506940000},
{"checked":true,"id":"170","title":"That pretty much all we have to do","date":"Aug 14 2013 15:02","time":1376506967000},
{"checked":true,"id":"169","title":"в то время как другие прибегают к повторным созданием их весь сайт на нужном языке и перенаправление пользователей","date":"Aug 14 2013 14:59","time":1376506786000},
{"checked":true,"id":"168","title":"while others have resorted to re-creating their entire site in the desired language and redirecting users based on their browser culture","date":"Aug 14 2013 15:00","time":1376506849000},
{"checked":true,"id":"167","title":"Между тем в тоже время вот временное решение","date":"Aug 14 2013 14:57","time":1376506662000},
{"checked":true,"id":"166","title":"In the meantime here is a temporary fix","date":"Aug 14 2013 14:58","time":1376506688000},
{"checked":true,"id":"165","title":"Для небольших приложений это Не может быть большим делом вы бы получали забирали эти данные при запуске и приклеивали","date":"Aug 14 2013 14:55","time":1376506506000},
{"checked":true,"id":"164","title":"For small applications it might not be a big deal you would fetch those data on app's startup and stick them into $rootScope but for huge ones it might get tricky","date":"Aug 14 2013 14:56","time":1376506618000},
{"checked":true,"id":"163","title":"Я думаю вы справились с этим","date":"Aug 14 2013 14:50","time":1376506210000},
{"checked":true,"id":"162","title":"I think you nailed it","date":"Aug 14 2013 14:50","time":1376506232000},
{"checked":true,"id":"161","title":"Я столкнулся поведением в Angular я не ожидал и цель этого поста выяснить является ли это ошибкой или намеренно","date":"Aug 14 2013 14:48","time":1376506103000},
{"checked":true,"id":"160","title":"I encountered behaviour in Angular I did not expect and the purpose of this post is to find out whether this is a bug or intended and possibly an explanation why it is intended","date":"Aug 14 2013 14:49","time":1376506175000},
{"checked":true,"id":"159","title":"Но этот код довольно ужасный","date":"Aug 14 2013 14:42","time":1376505739000},
{"checked":true,"id":"158","title":"But that code is pretty dreadful","date":"Aug 14 2013 14:42","time":1376505763000},
{"checked":true,"id":"157","title":"Такие вещи как правило лучше оставить для MS Excel","date":"Aug 14 2013 14:40","time":1376505658000},
{"checked":true,"id":"156","title":"This kind of thing is generally best left up to MS Excel","date":"Aug 14 2013 14:41","time":1376505681000},
{"checked":true,"id":"155","title":"AngularJS не был предназначен дляя управления этим изящно","date":"Aug 14 2013 14:38","time":1376505522000},
{"checked":true,"id":"154","title":"AngularJS was not designed to handle this gracefully","date":"Aug 14 2013 14:39","time":1376505554000},
{"checked":true,"id":"153","title":"Размещение вашей модели внутри объектной области гарантирует что AngularJS наблюдает за моделью и будет предпринимать","date":"Aug 14 2013 14:34","time":1376505281000},
{"checked":true,"id":"152","title":"Putting your model inside of a Scope object ensures that AngularJS is observing the model and will take any actions necessary if that model changes","date":"Aug 14 2013 14:36","time":1376505386000},
{"checked":true,"id":"151","title":"Ей не нужно интуитивно понимать правильный ответ или перелопачивать просматривать просеивать любой код","date":"Aug 14 2013 14:31","time":1376505070000},
{"checked":true,"id":"150","title":"She doesnt need to intuit the right answer or sift through any code","date":"Aug 14 2013 14:31","time":1376505110000},
{"checked":true,"id":"149","title":"Но не позволяйте JQuery стать костылем или вы никогда не овладеете AngularJS","date":"Aug 14 2013 14:28","time":1376504902000},
{"checked":true,"id":"148","title":"But dont let jQuery become a crutch or youll never master AngularJS","date":"Aug 14 2013 14:29","time":1376504943000},
{"checked":true,"id":"147","title":"в большинстве случаев плагин может быть переписан в в часть кода где вдруг все становится понятным и простым","date":"Aug 14 2013 14:25","time":1376504720000},
{"checked":true,"id":"146","title":"in most cases that plugin could be rewritten in AngularJS in a fraction of the code where suddenly everything becomes comprehensible and straightforward","date":"Aug 14 2013 14:26","time":1376504808000},
{"checked":true,"id":"145","title":"Многие разработчики создают эти продуманные решения которые они потом склеивают в AngularJS  с коллекцией callbacks это","date":"Aug 14 2013 12:53","time":1376499208000},
{"checked":true,"id":"144","title":"Many developers create these elaborate solutions that they then glue into AngularJS with a collection of callbacks  that are confusing and convoluted; but they eventually get it working","date":"Aug 14 2013 12:54","time":1376499290000},
{"checked":true,"id":"143","title":"Это потому, что JQuery был разработан для дополнения расширения усиливания и вырос невероятно из этой простой предпосылки","date":"Aug 13 2013 11:26","time":1376407578000},
{"checked":true,"id":"142","title":"This is because jQuery was designed for augmentation and has grown incredibly from that simple premise","date":"Aug 13 2013 11:27","time":1376407629000},
{"checked":true,"id":"141","title":"не дополняйте расширяйте усиливайте JQuery с AngularJS","date":"Aug 13 2013 11:12","time":1376406740000},
{"checked":true,"id":"140","title":"Dont Augment jQuery with AngularJS","date":"Aug 13 2013 11:23","time":1376407410000},
{"checked":true,"id":"139","title":"Может показаться что это большая работа, но на практике это довольно просто","date":"Aug 13 2013 11:09","time":1376406546000},
{"checked":true,"id":"138","title":"It might sound like it is a lot of work but in practice it is rather straightforward","date":"Aug 13 2013 11:10","time":1376406601000},
{"checked":true,"id":"137","title":"Я решил иметь различные конфиги","date":"Aug 13 2013 11:07","time":1376406456000},
{"checked":true,"id":"136","title":"I opted to have a different config","date":"Aug 13 2013 11:08","time":1376406484000},
{"checked":true,"id":"135","title":"Не поддавайтесь соблазну использовать эту сложную библиотеку в вашем контроллере","date":"Aug 13 2013 10:54","time":1376405692000},
{"checked":true,"id":"134","title":"Dont be tempted to use that complicated library in your controller","date":"Aug 13 2013 10:55","time":1376405715000},
{"checked":true,"id":"133","title":"Если у вас есть разрозненные контроллеры которые не разделяют общую сферу родителей","date":"Aug 13 2013 09:34","time":1376400879000},
{"checked":true,"id":"132","title":"If you have disparate controllers that do not share a common parent scope","date":"Aug 13 2013 09:35","time":1376400917000},
{"checked":true,"id":"131","title":"он предоставляет несколько удобных способов для Jasmine работать с AngularJS ","date":"Aug 13 2013 09:30","time":1376400630000},
{"checked":true,"id":"130","title":"it provides some convenience methods for Jasmine to work with AngularJS","date":"Aug 13 2013 09:32","time":1376400775000},
{"checked":true,"id":"129","title":"Таким образом не все JavaScript является правильным выражением","date":"Aug 13 2013 09:28","time":1376400507000},
{"checked":true,"id":"128","title":"As such not all JavaScript is a valid expression","date":"Aug 13 2013 09:28","time":1376400538000},
{"checked":true,"id":"127","title":"MVC обеспечивает слабую связь между этими слоями что позволяет слоям быть замененными","date":"Aug 13 2013 09:25","time":1376400334000},
{"checked":true,"id":"126","title":"MVC provides loose coupling between these layers that allow layers to be swappable","date":"Aug 13 2013 09:26","time":1376400383000},
{"checked":true,"id":"125","title":"Область разметка и услуги все входят в директиву и выводят разметку с JS функциональностью","date":"Aug 12 2013 13:07","time":1376327266000},
{"checked":true,"id":"124","title":"The scope markup and services all go into a directive and out comes markup with JS functionality","date":"Aug 12 2013 13:08","time":1376327336000},
{"checked":true,"id":"123","title":"Считайте что это аналогично jQuery","date":"Aug 12 2013 13:05","time":1376327111000},
{"checked":true,"id":"122","title":"Consider it analogous to jQuery ajax","date":"Aug 12 2013 13:05","time":1376327143000},
{"checked":true,"id":"121","title":"Я нашел изящный ясный способ использовать модули есть перезаписать встроенную директиву или две внутри одной","date":"Aug 12 2013 13:02","time":1376326963000},
{"checked":true,"id":"120","title":"Ive found a neat way to use modules is to say overwrite a built in directive or two within one","date":"Aug 12 2013 13:03","time":1376326992000},
{"checked":true,"id":"119","title":"Вам нужно установить некоторые пользовательские атрибуты или точнее директивы чтобы ваше AngularJS приложение  запустилось","date":"Aug 12 2013 12:59","time":1376326787000},
{"checked":true,"id":"118","title":"You need to set some custom attributes or more precisely directives to get your AngularJS application up and running","date":"Aug 12 2013 13:00","time":1376326848000},
{"checked":true,"id":"117","title":"Наконец мы рассмотрим некоторые рецепты для общих и не очень общих случаев использования","date":"Aug 12 2013 12:57","time":1376326644000},
{"checked":true,"id":"116","title":"Last we'll look at some recipes for common and not-so-common use cases","date":"Aug 12 2013 12:58","time":1376326684000},
{"checked":true,"id":"115","title":"Далее мы рассмотрим все эти понятия и более В изнурительных подробностях","date":"Aug 12 2013 12:55","time":1376326529000},
{"checked":true,"id":"114","title":"Next we'll cover all of these concepts and more in exhausting detail","date":"Aug 12 2013 12:56","time":1376326565000},
{"checked":true,"id":"113","title":"Сначала мы будем погружаться в основные понятия AngularJS","date":"Aug 12 2013 12:53","time":1376326434000},
{"checked":true,"id":"112","title":"First well dive into AngularJS basic concepts","date":"Aug 12 2013 12:54","time":1376326470000},
{"checked":true,"id":"111","title":"это колесо было изобретено бесчисленное количество раз","date":"Aug 12 2013 12:52","time":1376326363000},
{"checked":true,"id":"110","title":"this wheel has been invented countless times","date":"Aug 12 2013 12:53","time":1376326384000},
{"checked":true,"id":"109","title":"Шаблоны должны быть построены с чувствительной разметкой для мобильных дизайн будет доставлен предоставлен PSD макеты готовы","date":"Aug 12 2013 12:51","time":1376326274000},
{"checked":true,"id":"108","title":"Templates must be build with responsive markup for mobile design will be supplied the PSD layouts are ready to go","date":"Aug 12 2013 12:51","time":1376326303000},
{"checked":true,"id":"107","title":"Пожимать плечами отчет отчет об ошибке без сообщения об ошибке или воспроизведения шагов а лишь смутное описание проблемы","date":"Aug 12 2013 12:49","time":1376326143000},
{"checked":true,"id":"106","title":"Shrug Report bug report with no error message or repro steps and only a vague description of the problem","date":"Aug 12 2013 12:49","time":1376326174000},
{"checked":true,"id":"105","title":"Обрезать текст и добавить многоточие","date":"Aug 12 2013 12:47","time":1376326025000},
{"checked":true,"id":"104","title":"Truncate text and add ellipses","date":"Aug 12 2013 12:47","time":1376326050000},
{"checked":true,"id":"103","title":"Несмотря на то что я попытался","date":"Aug 12 2013 12:44","time":1376325889000},
{"checked":true,"id":"102","title":"Regardless I tried","date":"Aug 12 2013 12:45","time":1376325915000},
{"checked":true,"id":"101","title":"Этот пример очень надуманный но его должно быть достаточно чтобы проиллюстрировать вопрос","date":"Aug 12 2013 12:43","time":1376325805000},
{"checked":true,"id":"100","title":"This example is very contrive but should suffice to illustrate the point","date":"Aug 12 2013 12:43","time":1376325830000},
{"checked":true,"id":"99","title":"Там нет больше доставания с отсылкой документов по электронной почте туда и обратно","date":"Aug 12 2013 12:41","time":1376325688000},
{"checked":true,"id":"98","title":"Theres no more hassling with emailing documents back and forth","date":"Aug 12 2013 12:41","time":1376325718000},
{"checked":true,"id":"97","title":"Я использую обещания с моим get вызовом и я люблю как кратко и выразительно обещания делают мой код","date":"Aug 12 2013 12:37","time":1376325478000},
{"checked":true,"id":"96","title":"I am using promises with my $http.get call and I love how concise and expressive promises make my code","date":"Aug 12 2013 12:37","time":1376325479000},
{"checked":true,"id":"95","title":"Я все еще вижу что выражения в шаблонах по-прежнему неразрешены","date":"Aug 12 2013 12:37","time":1376325447000},
{"checked":true,"id":"94","title":"i still see that expressions in templates are still unresolved","date":"Aug 12 2013 12:37","time":1376325476000},
{"checked":true,"id":"93","title":"Количество вариантов является подавляющим огромным","date":"Aug 12 2013 12:35","time":1376325311000},
{"checked":true,"id":"92","title":"The number of options is overwhelming","date":"Aug 12 2013 12:35","time":1376325335000},
{"checked":true,"id":"91","title":"Чтобы не допустить этого мы добавляем сферу область видимости изолировать в наше определение директивы и таким образом избежать столкновения областей видимости","date":"Aug 12 2013 12:33","time":1376325198000},
{"checked":true,"id":"90","title":"To prevent that we add scope isolate to our directive definition and thus avoid scope clashes","date":"Aug 12 2013 12:33","time":1376325238000},
{"checked":true,"id":"89","title":"Дефицит означает что они очень нуждаются в капитале необходимом для роста и процветания","date":"Aug 12 2013 12:30","time":1376325007000},
{"checked":true,"id":"88","title":"The shortfall means they are starved of capital needed to grow and flourish","date":"Aug 12 2013 12:30","time":1376325054000},
{"checked":true,"id":"87","title":"Даже не смотра на то что по моему скромному мнению сердце это шаблон","date":"Aug 12 2013 12:27","time":1376324839000},
{"checked":true,"id":"86","title":"eventhough in my humble opinion the heart is the template","date":"Aug 12 2013 12:28","time":1376324929000},
{"checked":true,"id":"85","title":"вызов с помощью класса","date":"Aug 12 2013 12:24","time":1376324662000},
{"checked":true,"id":"84","title":"invocation via a class","date":"Aug 12 2013 12:24","time":1376324685000},
{"checked":true,"id":"83","title":"Я думаю что есть много неуместного раздражения в отношении обилия новых JavaScript фреймворков","date":"Aug 12 2013 12:22","time":1376324558000},
{"checked":true,"id":"82","title":"I think theres a lot of misplaced irritation regarding the abundance of new JavaScript frameworks","date":"Aug 12 2013 12:23","time":1376324592000},
{"checked":true,"id":"81","title":"Метод обходит DOM и сопоставляет директивы","date":"Aug 12 2013 12:21","time":1376324463000},
{"checked":true,"id":"80","title":"The method traverses the DOM and matches the directives","date":"Aug 12 2013 12:21","time":1376324491000},
{"checked":true,"id":"79","title":"Для того чтобы проиллюстрировать как Angular усиливает стандартный HTML","date":"Aug 12 2013 12:19","time":1376324357000},
{"checked":true,"id":"78","title":"In order to illustrate how Angular enhances standard HTML","date":"Aug 12 2013 12:20","time":1376324424000},
{"checked":true,"id":"77","title":"Там обязательно будут другие, более крайние случаи","date":"Aug 12 2013 12:16","time":1376324209000},
{"checked":true,"id":"76","title":"There are bound to be other more extreme cases_","date":"Aug 12 2013 12:17","time":1376324268000},
{"checked":true,"id":"75","title":"Все другие сценарии вне этой структуры постепенно будут включены в него","date":"Aug 12 2013 12:15","time":1376324114000},
{"checked":true,"id":"74","title":"All other scripts outside of this structure will gradually be incorporated into it","date":"Aug 12 2013 12:15","time":1376324138000},
{"checked":true,"id":"73","title":"мы можем быть гораздо более проворными с точки зрения новых изменений которые вы хотели бы чтобы попробовать не говоря уже о более согласованном A B тестировании","date":"Aug 12 2013 12:13","time":1376324007000},
{"checked":true,"id":"72","title":"we can then be a lot more agile in terms of new changes that youd like to try out not to mention a more coherent AB testing","date":"Aug 12 2013 12:14","time":1376324067000},
{"checked":true,"id":"71","title":"Не будем отвлекаться пока","date":"Aug 12 2013 12:08","time":1376323684000},
{"checked":true,"id":"70","title":"Lets not digress for now","date":"Aug 12 2013 12:08","time":1376323716000},
{"checked":true,"id":"69","title":"Мы можем ее распространять по всему сайту чтобы принести целостность","date":"Aug 12 2013 11:57","time":1376323034000},
{"checked":true,"id":"68","title":"we can have it propagate throughout the site to bring some cohesiveness","date":"Aug 12 2013 11:57","time":1376323060000},
{"checked":true,"id":"67","title":"Я фанат последовательности но чтобы не жертвовать опытом клиента от страницы к странице","date":"Aug 12 2013 11:55","time":1376322917000},
{"checked":true,"id":"66","title":"Im a fan of consistency but not to sacrifice a customers experience page-to-page","date":"Aug 12 2013 11:55","time":1376322953000},
{"checked":true,"id":"65","title":"Элементы в данном руководстве предназначены для повторного использования для обеспечения последовательности и ремонтопригодности","date":"Aug 12 2013 11:53","time":1376322801000},
{"checked":true,"id":"64","title":"the elements in this guide are meant to be reused for consistency and maintainability","date":"Aug 12 2013 11:53","time":1376322818000},
{"checked":true,"id":"63","title":"и мы можем подтвердить объем работы","date":"Aug 12 2013 11:50","time":1376322602000},
{"checked":true,"id":"62","title":"and we can confirm the workload","date":"Aug 12 2013 11:50","time":1376322629000},
{"checked":true,"id":"61","title":"По этой причине я также рассматриваю более полный капитальный ремонт используя angularjs","date":"Aug 12 2013 11:48","time":1376322521000},
{"checked":true,"id":"60","title":"For that reason Im also considering a more complete overhaul using angularjs","date":"Aug 12 2013 11:49","time":1376322543000},
{"checked":true,"id":"59","title":"подключить бекэнд","date":"Aug 12 2013 11:46","time":1376322386000},
{"checked":true,"id":"58","title":"Wire up a Backend","date":"Aug 12 2013 11:47","time":1376322423000},
{"checked":true,"id":"57","title":"Основные различия изложены хорошо в ответах","date":"Aug 11 2013 22:42","time":1376275372000},
{"checked":true,"id":"56","title":"The major differences are outlined well in the answers","date":"Aug 11 2013 22:43","time":1376275391000},
{"checked":true,"id":"55","title":"Наши вкладки будут менее склонны к поломке, если мы используем Min Width взамен","date":"Aug 11 2013 22:39","time":1376275152000},
{"checked":true,"id":"54","title":"Our tabs would be less prone to breakage if we use min width instead","date":"Aug 11 2013 22:39","time":1376275199000},
{"checked":true,"id":"53","title":"Определяет от тонких до толстых символов","date":"Aug 11 2013 22:38","time":1376275082000},
{"checked":true,"id":"52","title":"Defines from thin to thick characters","date":"Aug 11 2013 22:38","time":1376275107000},
{"checked":true,"id":"51","title":"Я нашел это временное решение для устранения этой проблемы","date":"Aug 11 2013 22:31","time":1376274670000},
{"checked":true,"id":"50","title":"I found this workaround to fix this issue","date":"Aug 11 2013 22:31","time":1376274694000},
{"checked":true,"id":"49","title":"Этот резервный шрифт может иметь совершенно разные размеры","date":"Aug 11 2013 22:29","time":1376274596000},
{"checked":true,"id":"48","title":"That fallback font might have drastically different sizing","date":"Aug 11 2013 22:30","time":1376274632000},
{"checked":true,"id":"47","title":"Этот конкретный пример немного надуманный","date":"Aug 11 2013 22:28","time":1376274524000},
{"checked":true,"id":"46","title":"This particular example is a bit contrived","date":"Aug 11 2013 22:29","time":1376274548000},
{"checked":true,"id":"45","title":"Разве второй просто не зверский ","date":"Aug 11 2013 22:26","time":1376274417000},
{"checked":true,"id":"44","title":"Isn't the second one simply atrocious","date":"Aug 11 2013 22:27","time":1376274438000},
{"checked":true,"id":"43","title":"Но заикание было довольно постоянным","date":"Aug 11 2013 22:25","time":1376274300000},
{"checked":true,"id":"42","title":"But the stuttering was pretty constant","date":"Aug 11 2013 22:25","time":1376274324000},
{"checked":true,"id":"41","title":"по прежнему есть лаги при сборе монет","date":"Aug 11 2013 22:21","time":1376274110000},
{"checked":true,"id":"40","title":"Its still a bit laggy when collecting a coin","date":"Aug 11 2013 22:22","time":1376274135000},
{"checked":true,"id":"39","title":"Частота кадров заикается заметно на iPhone","date":"Aug 11 2013 22:16","time":1376273790000},
{"checked":true,"id":"38","title":"Framerate stutters noticeably on iPhone","date":"Aug 11 2013 22:17","time":1376273850000},
{"checked":true,"id":"37","title":"Я хочу извлечь значение y прямоугольной группы","date":"Aug 11 2013 22:14","time":1376273665000},
{"checked":true,"id":"36","title":"I want to retrieve the y value of the rectangle group","date":"Aug 11 2013 22:14","time":1376273696000},
{"checked":true,"id":"35","title":"Вы знаете сколько времени может быть потеряно из-за едва уловимых недостатков в коде","date":"Aug 11 2013 22:11","time":1376273494000},
{"checked":true,"id":"34","title":"You know how much time can be lost to subtle flaws in your code","date":"Aug 11 2013 22:12","time":1376273534000},
{"checked":true,"id":"33","title":"При выполнении if checks операторы присваивания иногда могут быть опущены","date":"Aug 11 2013 22:08","time":1376273310000},
{"checked":true,"id":"32","title":"When doing “if checks” assignment operators can sometimes be omitted","date":"Aug 11 2013 22:08","time":1376273324000},
{"checked":true,"id":"31","title":"Люди, которые так или иначе попали в роли программиста без йоты специальных знаний или способностей","date":"Aug 11 2013 13:23","time":1376241833000},
{"checked":true,"id":"30","title":"People who somehow fell into the programmer role without an iota of skill or ability","date":"Aug 11 2013 13:24","time":1376241868000},
{"checked":true,"id":"29","title":"вы найдете что-то подобное, что по крайней мере частично напоминает вашу проблему","date":"Aug 11 2013 13:19","time":1376241549000},
{"checked":true,"id":"28","title":"you find something similar that at least partially resembles your problem","date":"Aug 11 2013 13:19","time":1376241581000},
{"checked":true,"id":"27","title":"какой хороший подход","date":"Aug 11 2013 13:16","time":1376241388000},
{"checked":true,"id":"26","title":"what is a good approach","date":"Aug 11 2013 13:16","time":1376241416000},
{"checked":true,"id":"25","title":"незавершенноe заявление","date":"Aug 11 2013 13:04","time":1376240666000},
{"checked":true,"id":"24","title":"unterminated statement","date":"Aug 11 2013 13:04","time":1376240680000},
{"checked":true,"id":"23","title":"для достижения этой цели","date":"Aug 10 2013 17:23","time":1376169818000},
{"checked":true,"id":"22","title":"to accomplish this","date":"Aug 10 2013 17:24","time":1376169889000},
{"checked":true,"id":"21","title":"Это может быть очень тонким хитроумным багом","date":"Aug 10 2013 17:21","time":1376169687000},
{"checked":true,"id":"20","title":"This can be a very subtle bug","date":"Aug 10 2013 17:22","time":1376169763000},
{"checked":true,"id":"19","title":"Там обязательно будут другие более крайние случаи","date":"Aug 10 2013 17:19","time":1376169554000},
{"checked":true,"id":"18","title":"there are bound to be other more extreme cases","date":"Aug 10 2013 17:20","time":1376169621000},
{"checked":true,"id":"17","title":"Первое что приходит на ум","date":"Aug 10 2013 17:17","time":1376169477000},
{"checked":true,"id":"16","title":"the first thing that comes to mind","date":"Aug 10 2013 17:18","time":1376169491000},
{"checked":true,"id":"15","title":"Это было бы крайне неэффективно","date":"Aug 10 2013 17:15","time":1376169311000},
{"checked":true,"id":"14","title":"That would be grossly inefficient","date":"Aug 10 2013 17:16","time":1376169396000},
{"checked":true,"id":"13","title":"это не жизнеспособный вариант","date":"Aug 10 2013 17:13","time":1376169201000},
{"checked":true,"id":"12","title":"Its not a viable option","date":"Aug 10 2013 17:14","time":1376169246000},
{"checked":true,"id":"11","title":"Было очевидно что мне нужно было поправить откоректировать вещи немного","date":"Aug 10 2013 17:11","time":1376169108000},
{"checked":true,"id":"10","title":"It was apparent that I needed to tweak things a bit","date":"Aug 10 2013 17:12","time":1376169145000},
{"checked":true,"id":"9","title":"Она работает довольно прилично","date":"Aug 10 2013 17:09","time":1376168954000},
{"checked":true,"id":"8","title":"It runs pretty decent","date":"Aug 10 2013 17:10","time":1376169005000},
{"checked":true,"id":"7","title":"я очень настороженно отношусь к хмл","date":"Aug 10 2013 17:07","time":1376168874000},
{"checked":true,"id":"6","title":"Im deeply ambivalent about XML","date":"Aug 10 2013 17:08","time":1376168911000},
{"checked":true,"id":"5","title":"Если изменения это не так много хлопот","date":"Aug 10 2013 17:05","time":1376168756000},
{"checked":true,"id":"4","title":"if changing is not much of a hassle","date":"Aug 10 2013 17:06","time":1376168790000},
{"checked":true,"id":"3","title":"потому что это подразумевается","date":"Aug 10 2013 17:03","time":1376168612000},
{"checked":true,"id":"2","title":"because it is implied","date":"Aug 10 2013 17:04","time":1376168644000},
{"checked":true,"id":"1","title":"Желание обуздать  визуальные излишества и устранить фальшивки","date":"Aug 10 2013 17:01","time":1376168478000},
{"checked":true,"id":"0","title":"a desire to curb visual excess and eliminate the fake and the superfluous","date":"Aug 10 2013 17:01","time":1376168506000}
]}